dachi/__init__.py
dachi/_core/__init__.py
dachi/_core/_ai.py
dachi/_core/_core.py
dachi/_core/_instruct.py
dachi/_core/_process.py
dachi/_core/_read.py
dachi/act/__init__.py
dachi/act/_agent.py
dachi/act/_build.py
dachi/act/_core.py
dachi/act/_decorator_func.py
dachi/act/_functional.py
dachi/act/_tasks.py
dachi/adapt/__init__.py
dachi/adapt/anthropic.py
dachi/adapt/gemini.py
dachi/adapt/openai.py
dachi/adapt/voyage.py
dachi/data/__init__.py
dachi/data/_data.py
dachi/data/_lang.py
dachi/data/_structs.py
dachi/graph/__init__.py
dachi/graph/_core.py
dachi/graph/_network.py
dachi/op/__init__.py
dachi/op/_data.py
dachi/op/_instruct.py
dachi/read/__init__.py
dachi/read/_read.py
dachi/utils/__init__.py
dachi/utils/_model.py
dachi/utils/_utils.py
dachi-0.0.1.dist-info/LICENSE
dachi-0.0.1.dist-info/METADATA
dachi-0.0.1.dist-info/WHEEL
dachi-0.0.1.dist-info/RECORD
