Metadata-Version: 2.1
Name: dachi
Version: 0.0.1
Summary: A framework for flexibly creating AI agents.
Home-page: https://github.com/short-greg/dachi
License: LICENSE
Author: Greg Short
Author-email: g.short@kurenai.waseda.jp
Requires-Python: >=3.10,<4.0
Classifier: License :: Other/Proprietary License
Classifier: Programming Language :: Python :: 3
Classifier: Programming Language :: Python :: 3.10
Classifier: Programming Language :: Python :: 3.11
Classifier: Programming Language :: Python :: 3.12
Classifier: Programming Language :: Python :: 3.13
Requires-Dist: networkx (>=3.0,<4.0)
Requires-Dist: numpy (>=1.0)
Requires-Dist: pandas (>=1.0)
Requires-Dist: pydantic (>=2,<3)
Requires-Dist: pytest (>=7,<8)
Requires-Dist: roman (>=4,<5)
Project-URL: Documentation, https://dachi.readthedocs.com
Project-URL: Repository, https://github.com/short-greg/dachi
